flamapy/interfaces/rest/operations_routes.py
flamapy_rest-2.0.0.dist-info/METADATA
flamapy_rest-2.0.0.dist-info/WHEEL
flamapy_rest-2.0.0.dist-info/top_level.txt
flamapy_rest-2.0.0.dist-info/RECORD
